oriole/__init__.py
oriole/alg.so
oriole/cli.py
oriole/db.py
oriole/eric.py
oriole/fake.py
oriole/log.py
oriole/ops.py
oriole/vos.py
oriole/yml.py
oriole-22.1.0.dist-info/LICENSE
oriole-22.1.0.dist-info/METADATA
oriole-22.1.0.dist-info/WHEEL
oriole-22.1.0.dist-info/top_level.txt
oriole-22.1.0.dist-info/zip-safe
oriole-22.1.0.dist-info/RECORD
