Metadata-Version: 2.1
Name: oriole
Version: 22.1.0
Summary: vos
Home-page: https://github.com/zhouxiaoxiang/oriole
Author: Eric.Zhou
Author-email: xiaoxiang.cn@gmail.com
License: Apache License, Version 2.0
Platform: UNKNOWN
Classifier: Programming Language :: Python
Classifier: Programming Language :: Python :: 3.6
Classifier: Programming Language :: Python :: 3.7
Classifier: Operating System :: POSIX
Classifier: Topic :: Internet
Classifier: Topic :: Software Development :: Libraries :: Python Modules
Classifier: Intended Audience :: Developers
Requires-Python: >=3.6
Requires-Dist: pyyaml (>=5.1)
Requires-Dist: SQLAlchemy (>=1.2.14)
Requires-Dist: mogo (>=0.4.0)
Requires-Dist: redis (>=2.10.6)
Requires-Dist: Babel (>=2.5.3)
Requires-Dist: PyMySQL (>=0.7.11)
Requires-Dist: mysqlclient (>=1.3.12)
Requires-Dist: pytest (>=3.2.3)
Requires-Dist: Sphinx (>=1.7.2)
Requires-Dist: mockredispy (>=2.9.3)
Requires-Dist: mongomock (>=3.8.0)
